fuzzypandaswuzzy/README.MD
fuzzypandaswuzzy/__init__.py
fuzzypandaswuzzy/requirements.txt
fuzzypandaswuzzy/thirdparty.json
fuzzypandaswuzzy-0.10.dist-info/LICENSE.rst
fuzzypandaswuzzy-0.10.dist-info/METADATA
fuzzypandaswuzzy-0.10.dist-info/WHEEL
fuzzypandaswuzzy-0.10.dist-info/top_level.txt
fuzzypandaswuzzy-0.10.dist-info/RECORD
