Metadata-Version: 2.1
Name: fuzzypandaswuzzy
Version: 0.10
Summary: Fuzzy Comparison Utilities for DataFrame Columns
Home-page: https://github.com/hansalemaos/fuzzypandaswuzzy
Author: Johannes Fischer
Author-email: aulasparticularesdealemaosp@gmail.com
License: MIT
Keywords: fuzzy,wuzzy,pandas
Classifier: Development Status :: 4 - Beta
Classifier: Programming Language :: Python :: 3 :: Only
Classifier: Programming Language :: Python :: 3.10
Classifier: Topic :: Software Development :: Libraries :: Python Modules
Classifier: Topic :: Utilities
License-File: LICENSE.rst
Requires-Dist: numpy
Requires-Dist: pandas
Requires-Dist: rapidfuzz
